flask_mongorest/__init__.py
flask_mongorest/authentication.py
flask_mongorest/exceptions.py
flask_mongorest/methods.py
flask_mongorest/operators.py
flask_mongorest/resources.py
flask_mongorest/utils.py
flask_mongorest/views.py
flask_mongorest/templates/mongorest/debug.html
Flask_MongoRest-0.3.0.dist-info/AUTHORS
Flask_MongoRest-0.3.0.dist-info/LICENSE
Flask_MongoRest-0.3.0.dist-info/METADATA
Flask_MongoRest-0.3.0.dist-info/WHEEL
Flask_MongoRest-0.3.0.dist-info/top_level.txt
Flask_MongoRest-0.3.0.dist-info/RECORD
