Metadata-Version: 2.1
Name: Flask-MongoRest
Version: 0.3.0
Summary: Flask restful API framework for MongoDB/MongoEngine
Home-page: http://github.com/closeio/flask-mongorest
Author: Close.io
Author-email: engineering@close.io
Maintainer: Close.io
Maintainer-email: engineering@close.io
License: BSD
Platform: any
Classifier: Development Status :: 4 - Beta
Classifier: Environment :: Web Environment
Classifier: Intended Audience :: Developers
Classifier: License :: OSI Approved :: BSD License
Classifier: Operating System :: OS Independent
Classifier: Programming Language :: Python
Classifier: Topic :: Internet :: WWW/HTTP :: Dynamic Content
Classifier: Topic :: Software Development :: Libraries :: Python Modules
